mognet/__init__.py
mognet/__main__.py
mognet/app/__init__.py
mognet/app/app.py
mognet/app/app_config.py
mognet/backend/__init__.py
mognet/backend/backend_config.py
mognet/backend/base_result_backend.py
mognet/backend/memory_result_backend.py
mognet/backend/redis_result_backend.py
mognet/broker/__init__.py
mognet/broker/amqp_broker.py
mognet/broker/base_broker.py
mognet/broker/broker_config.py
mognet/broker/memory_broker.py
mognet/cli/__init__.py
mognet/cli/cli_state.py
mognet/cli/exceptions.py
mognet/cli/main.py
mognet/cli/models.py
mognet/cli/nodes.py
mognet/cli/queues.py
mognet/cli/run.py
mognet/cli/run_in_loop.py
mognet/cli/tasks.py
mognet/context/__init__.py
mognet/context/context.py
mognet/decorators/__init__.py
mognet/decorators/task_decorator.py
mognet/exceptions/__init__.py
mognet/exceptions/base_exceptions.py
mognet/exceptions/broker_exceptions.py
mognet/exceptions/result_exceptions.py
mognet/exceptions/task_exceptions.py
mognet/exceptions/too_many_retries.py
mognet/middleware/__init__.py
mognet/middleware/middleware.py
mognet/model/__init__.py
mognet/model/queue_stats.py
mognet/model/result.py
mognet/model/result_state.py
mognet/model/result_tree.py
mognet/primitives/__init__.py
mognet/primitives/queries.py
mognet/primitives/request.py
mognet/primitives/revoke.py
mognet/py.typed
mognet/service/__init__.py
mognet/service/class_service.py
mognet/state/__init__.py
mognet/state/base_state_backend.py
mognet/state/redis_state_backend.py
mognet/state/state.py
mognet/state/state_backend_config.py
mognet/tasks/__init__.py
mognet/tasks/task_registry.py
mognet/testing/__init__.py
mognet/testing/pytest_integration.py
mognet/tools/__init__.py
mognet/tools/backports/__init__.py
mognet/tools/backports/aioitertools.py
mognet/tools/dates.py
mognet/tools/kwargs_repr.py
mognet/tools/retries.py
mognet/tools/urls.py
mognet/worker/__init__.py
mognet/worker/worker.py
mognet-2.0.0.dist-info/LICENSE
mognet-2.0.0.dist-info/METADATA
mognet-2.0.0.dist-info/WHEEL
mognet-2.0.0.dist-info/entry_points.txt
mognet-2.0.0.dist-info/RECORD
