Metadata-Version: 2.1
Name: mognet
Version: 2.0.0
Summary: Mognet is a fast, simple framework to build distributed applications using task queues.
Home-page: https://ds4sd.github.io/project-mognet/
License: MIT
Author: André Carvalho
Author-email: afecarvalho@gmail.com
Requires-Python: >=3.8,<4.0
Classifier: Development Status :: 5 - Production/Stable
Classifier: License :: OSI Approved :: MIT License
Classifier: Programming Language :: Python :: 3
Classifier: Programming Language :: Python :: 3.8
Classifier: Programming Language :: Python :: 3.9
Classifier: Programming Language :: Python :: 3.10
Classifier: Programming Language :: Python :: 3.11
Classifier: Programming Language :: Python :: 3.12
Classifier: Topic :: Software Development :: Libraries :: Python Modules
Classifier: Topic :: Software Development :: Version Control :: Git
Classifier: Typing :: Typed
Requires-Dist: aio-pika (>=6.8.0,<7.0.0)
Requires-Dist: aiorun (>=2021.10.1,<2022.0.0)
Requires-Dist: pydantic (>=2,<3)
Requires-Dist: redis[hiredis] (>=4.2.2,<5.0.0)
Requires-Dist: tabulate (>=0.8.9,<1)
Requires-Dist: treelib (>=1.6.0,<2.0.0)
Requires-Dist: typer (>=0.9.0,<0.10.0)
Requires-Dist: typing-extensions (>=3.10.0.0) ; python_version < "3.10"
Project-URL: Documentation, https://ds4sd.github.io/project-mognet/
Project-URL: Repository, https://github.com/DS4SD/project-mognet
